pyprithvi/__init__.py
pyprithvi/data.py
pyprithvi/delete.py
pyprithvi/engine.py
pyprithvi/job.py
pyprithvi/primitives.py
pyprithvi/user.py
pyprithvi/utils/__init__.py
pyprithvi/utils/serialization.py
pyprithvi-0.0.2.dist-info/METADATA
pyprithvi-0.0.2.dist-info/WHEEL
pyprithvi-0.0.2.dist-info/top_level.txt
pyprithvi-0.0.2.dist-info/RECORD
